odoo10_addon_barcodes_search-10.0.1.0.2-nspkg.pth
odoo/addons/barcodes_search/README.rst
odoo/addons/barcodes_search/__init__.py
odoo/addons/barcodes_search/__manifest__.py
odoo/addons/barcodes_search/demo/product_product.xml
odoo/addons/barcodes_search/demo/res_partner.xml
odoo/addons/barcodes_search/i18n/barcodes_search.pot
odoo/addons/barcodes_search/i18n/fr.po
odoo/addons/barcodes_search/i18n/fr_1.po
odoo/addons/barcodes_search/readme/CONTRIBUTORS.rst
odoo/addons/barcodes_search/readme/DESCRIPTION.rst
odoo/addons/barcodes_search/readme/DEVELOP.rst
odoo/addons/barcodes_search/readme/USAGE.rst
odoo/addons/barcodes_search/static/description/barcode_button_menu.png
odoo/addons/barcodes_search/static/description/icon.png
odoo/addons/barcodes_search/static/description/index.html
odoo/addons/barcodes_search/static/description/partner_search.png
odoo/addons/barcodes_search/static/description/partner_user_search.png
odoo/addons/barcodes_search/static/description/price_product_search.png
odoo/addons/barcodes_search/static/src/js/barcodes_search.js
odoo/addons/barcodes_search/static/src/xml/barcodes_search.xml
odoo/addons/barcodes_search/tests/__init__.py
odoo/addons/barcodes_search/tests/test_barcode_search.py
odoo/addons/barcodes_search/views/templates.xml
odoo/addons/barcodes_search/wizards/__init__.py
odoo/addons/barcodes_search/wizards/barcode_search.py
odoo/addons/barcodes_search/wizards/barcode_search_line.py
odoo/addons/barcodes_search/wizards/barcode_search_view.xml
odoo10_addon_barcodes_search-10.0.1.0.2.dist-info/METADATA
odoo10_addon_barcodes_search-10.0.1.0.2.dist-info/WHEEL
odoo10_addon_barcodes_search-10.0.1.0.2.dist-info/namespace_packages.txt
odoo10_addon_barcodes_search-10.0.1.0.2.dist-info/top_level.txt
odoo10_addon_barcodes_search-10.0.1.0.2.dist-info/RECORD
